smartreply/smartreply.cpython-36m-x86_64-linux-gnu.so
smartreply/model.tflite
smartreply/__init__.py
smartreply/lib64/libre2.a
smartreply/lib64/cmake/re2/re2Config-release.cmake
smartreply/lib64/cmake/re2/re2Config.cmake
smartreply/include/re2/stringpiece.h
smartreply/include/re2/re2.h
smartreply/include/re2/filtered_re2.h
smartreply/include/re2/set.h
py_smartreply-0.0.1.dist-info/LICENSE
py_smartreply-0.0.1.dist-info/METADATA
py_smartreply-0.0.1.dist-info/top_level.txt
py_smartreply-0.0.1.dist-info/WHEEL
py_smartreply-0.0.1.dist-info/RECORD
